riverbank/__init__.py
riverbank-0.0.1.dist-info/LICENSE.txt
riverbank-0.0.1.dist-info/METADATA
riverbank-0.0.1.dist-info/WHEEL
riverbank-0.0.1.dist-info/top_level.txt
riverbank-0.0.1.dist-info/RECORD
